vapl_compiler/__init__.py
vapl_compiler-0.1.0.dist-info/METADATA
vapl_compiler-0.1.0.dist-info/WHEEL
vapl_compiler-0.1.0.dist-info/top_level.txt
vapl_compiler-0.1.0.dist-info/RECORD
