Metadata-Version: 2.1
Name: vapl-compiler
Version: 0.1.0
Summary: A compiler for VAPL
Home-page: http://replit.com/@WWWtheW/vaplcompiler
Author: WWWtheW
Author-email: dontmailme@dontthinkaboutmailingmebecausemyemailisprivate.com
License: MIT
Platform: UNKNOWN
